ddtrace_asgi/__init__.py
ddtrace_asgi/__version__.py
ddtrace_asgi/middleware.py
ddtrace_asgi/py.typed
ddtrace_asgi-0.3.0.dist-info/LICENSE
ddtrace_asgi-0.3.0.dist-info/METADATA
ddtrace_asgi-0.3.0.dist-info/WHEEL
ddtrace_asgi-0.3.0.dist-info/top_level.txt
ddtrace_asgi-0.3.0.dist-info/RECORD
