Metadata-Version: 2.1
Name: ddtrace-asgi
Version: 0.3.0
Summary: Unofficial ddtrace integration for ASGI apps and frameworks
Home-page: http://github.com/florimondmanca/ddtrace-asgi
Author: Florimond Manca
Author-email: florimond.manca@gmail.com
License: BSD
Platform: UNKNOWN
Classifier: Development Status :: 3 - Alpha
Classifier: Intended Audience :: Developers
Classifier: Operating System :: OS Independent
Classifier: Programming Language :: Python :: 3
Classifier: Programming Language :: Python :: 3.6
Classifier: Programming Language :: Python :: 3.7
Classifier: Programming Language :: Python :: 3.8
Requires-Python: >=3.6
Requires-Dist: ddtrace
Requires-Dist: starlette (==0.*)
